polyglot/__init__.py
polyglot/__main__.py
polyglot/base.py
polyglot/decorators.py
polyglot/downloader.py
polyglot/load.py
polyglot/mixins.py
polyglot/text.py
polyglot/utils.py
polyglot/detect/__init__.py
polyglot/detect/base.py
polyglot/detect/langids.py
polyglot/mapping/__init__.py
polyglot/mapping/base.py
polyglot/mapping/embeddings.py
polyglot/mapping/expansion.py
polyglot/tag/__init__.py
polyglot/tag/base.py
polyglot/tokenize/__init__.py
polyglot/tokenize/base.py
polyglot/transliteration/__init__.py
polyglot/transliteration/base.py
polyglot_fork-16.7.4.dist-info/AUTHORS.rst
polyglot_fork-16.7.4.dist-info/LICENSE
polyglot_fork-16.7.4.dist-info/METADATA
polyglot_fork-16.7.4.dist-info/WHEEL
polyglot_fork-16.7.4.dist-info/entry_points.txt
polyglot_fork-16.7.4.dist-info/top_level.txt
polyglot_fork-16.7.4.dist-info/RECORD
